ldndc2nc/__init__.py
ldndc2nc/__main__.py
ldndc2nc/_version.py
ldndc2nc/cli.py
ldndc2nc/extra.py
ldndc2nc/ldndc2nc.py
ldndc2nc/data/__init__.py
ldndc2nc/test/__init__.py
ldndc2nc-0.1.0.dist-info/LICENSE.md
ldndc2nc-0.1.0.dist-info/METADATA
ldndc2nc-0.1.0.dist-info/WHEEL
ldndc2nc-0.1.0.dist-info/entry_points.txt
ldndc2nc-0.1.0.dist-info/top_level.txt
ldndc2nc-0.1.0.dist-info/RECORD
