Metadata-Version: 2.1
Name: ldndc2nc
Version: 0.1.0
Summary: LandscapeDNDC inventory postprocessor to netCDF format
Home-page: https://www.github.com/cwerner/ldndc2nc
Author: Christian Werner
Author-email: christian.werner@kit.edu
License: BSD 3-Clause License
Platform: UNKNOWN
Classifier: Development Status :: 4 - Beta
Classifier: Environment :: Console
Classifier: Intended Audience :: Developers
Classifier: License :: OSI Approved :: MIT License
Classifier: Operating System :: MacOS :: MacOS X
Classifier: Operating System :: Microsoft :: Windows
Classifier: Operating System :: POSIX
Classifier: Operating System :: POSIX :: Linux
Classifier: Programming Language :: Python :: 3.6
Classifier: Programming Language :: Python :: 3.7
Classifier: Programming Language :: Python :: 3.8
Classifier: Topic :: Software Development
Requires-Dist: netcdf4
Requires-Dist: numpy
Requires-Dist: param
Requires-Dist: pandas
Requires-Dist: pyyaml
Requires-Dist: xarray
